ic/__init__.py
icode/__init__.py
icolor/__init__.py
icodetoyou-0.0.6.dist-info/LICENSE
icodetoyou-0.0.6.dist-info/METADATA
icodetoyou-0.0.6.dist-info/WHEEL
icodetoyou-0.0.6.dist-info/top_level.txt
icodetoyou-0.0.6.dist-info/RECORD
